chkw/__init__.py
chkw/cli.py
chkw/evaluator/__init__.py
chkw/tokenizer/__init__.py
chkw/transcompiler/__init__.py
chkw-0.1.5.dist-info/METADATA
chkw-0.1.5.dist-info/WHEEL
chkw-0.1.5.dist-info/entry_points.txt
chkw-0.1.5.dist-info/top_level.txt
chkw-0.1.5.dist-info/RECORD
