Metadata-Version: 2.1
Name: chkw
Version: 0.1.5
Requires-Dist: Click
